{
	"name": "Silver",
	"properties": {
		"activities": [
			{
				"name": "Silver DF",
				"type": "ExecuteDataFlow",
				"dependsOn": [],
				"policy": {
					"timeout": "0.12:00:00",
					"retry": 0,
					"retryIntervalInSeconds": 30,
					"secureOutput": false,
					"secureInput": false
				},
				"userProperties": [],
				"typeProperties": {
					"dataflow": {
						"referenceName": "Metadata_Silver",
						"type": "DataFlowReference",
						"datasetParameters": {
							"MetadataCols": {
								"Directoryname": "Metadata/Processed"
							},
							"KeyCols": {
								"Directoryname": "Metadata/Key_Cols"
							},
							"sink1": {
								"Directoryname": "Metadata/Key_Cols_Silver"
							}
						}
					},
					"compute": {
						"coreCount": 8,
						"computeType": "General"
					},
					"traceLevel": "Fine"
				}
			}
		],
		"annotations": []
	}
}